[
  {
    "id": 1122,
    "quiz_id": 122,
    "quiz_group_id": null,
    "assessment_question_id": 1122,
    "position": null,
    "question_name": "Câu hỏi",
    "question_type": "multiple_choice_question",
    "question_text": "<p>Quản lý nguồn nhân lực dự án là gì?</p>",
    "points_possible": 1.0,
    "correct_comments": "",
    "incorrect_comments": "",
    "neutral_comments": "",
    "correct_comments_html": "",
    "incorrect_comments_html": "",
    "neutral_comments_html": "",
    "answers": [
      {
        "id": 1458,
        "text": "Quá trình lập kế hoạch, tổ chức và điều phối con người để đạt mục tiêu dự án",
        "html": "",
        "comments": "",
        "comments_html": "",
        "weight": 100.0
      },
      {
        "id": 6176,
        "text": "Theo dõi ngân sách",
        "html": "",
        "comments": "",
        "comments_html": "",
        "weight": 0.0
      },
      {
        "id": 3941,
        "text": "Lập kế hoạch tiến độ",
        "html": "",
        "comments": "",
        "comments_html": "",
        "weight": 0.0
      },
      {
        "id": 2600,
        "text": "Thiết kế hệ thống",
        "html": "",
        "comments": "",
        "comments_html": "",
        "weight": 0.0
      }
    ],
    "variables": null,
    "formulas": null,
    "answer_tolerance": null,
    "formula_decimal_places": null,
    "matches": null,
    "matching_answer_incorrect_matches": null
  },
  {
    "id": 1123,
    "quiz_id": 122,
    "quiz_group_id": null,
    "assessment_question_id": 1123,
    "position": null,
    "question_name": "Câu hỏi",
    "question_type": "multiple_choice_question",
    "question_text": "<p>Thuyết X của McGregor cho rằng:</p>",
    "points_possible": 1.0,
    "correct_comments": "",
    "incorrect_comments": "",
    "neutral_comments": "",
    "correct_comments_html": "",
    "incorrect_comments_html": "",
    "neutral_comments_html": "",
    "answers": [
      {
        "id": 5626,
        "text": "Nhân viên cần được giám sát chặt chẽ và tránh trách nhiệm",
        "html": "",
        "comments": "",
        "comments_html": "",
        "weight": 100.0
      },
      {
        "id": 4813,
        "text": "Nhân viên tự giác và sáng tạo",
        "html": "",
        "comments": "",
        "comments_html": "",
        "weight": 0.0
      },
      {
        "id": 952,
        "text": "Nhân viên thích được trao quyền",
        "html": "",
        "comments": "",
        "comments_html": "",
        "weight": 0.0
      },
      {
        "id": 248,
        "text": "Nhân viên chủ động hợp tác",
        "html": "",
        "comments": "",
        "comments_html": "",
        "weight": 0.0
      }
    ],
    "variables": null,
    "formulas": null,
    "answer_tolerance": null,
    "formula_decimal_places": null,
    "matches": null,
    "matching_answer_incorrect_matches": null
  },
  {
    "id": 1124,
    "quiz_id": 122,
    "quiz_group_id": null,
    "assessment_question_id": 1124,
    "position": null,
    "question_name": "Câu hỏi",
    "question_type": "multiple_choice_question",
    "question_text": "<p>Giai đoạn 'Storming' trong mô hình Tuckman biểu thị điều gì?</p>",
    "points_possible": 1.0,
    "correct_comments": "",
    "incorrect_comments": "",
    "neutral_comments": "",
    "correct_comments_html": "",
    "incorrect_comments_html": "",
    "neutral_comments_html": "",
    "answers": [
      {
        "id": 6601,
        "text": "Nhóm xuất hiện xung đột ý kiến",
        "html": "",
        "comments": "",
        "comments_html": "",
        "weight": 100.0
      },
      {
        "id": 6191,
        "text": "Nhóm đang làm việc hiệu quả cao",
        "html": "",
        "comments": "",
        "comments_html": "",
        "weight": 0.0
      },
      {
        "id": 1763,
        "text": "Nhóm tan rã",
        "html": "",
        "comments": "",
        "comments_html": "",
        "weight": 0.0
      },
      {
        "id": 1240,
        "text": "Nhóm được hình thành ban đầu",
        "html": "",
        "comments": "",
        "comments_html": "",
        "weight": 0.0
      }
    ],
    "variables": null,
    "formulas": null,
    "answer_tolerance": null,
    "formula_decimal_places": null,
    "matches": null,
    "matching_answer_incorrect_matches": null
  },
  {
    "id": 1125,
    "quiz_id": 122,
    "quiz_group_id": null,
    "assessment_question_id": 1125,
    "position": null,
    "question_name": "Câu hỏi",
    "question_type": "multiple_choice_question",
    "question_text": "<p>Theo Maslow, nhu cầu cao nhất của con người là:</p>",
    "points_possible": 1.0,
    "correct_comments": "",
    "incorrect_comments": "",
    "neutral_comments": "",
    "correct_comments_html": "",
    "incorrect_comments_html": "",
    "neutral_comments_html": "",
    "answers": [
      {
        "id": 5915,
        "text": "Tự hoàn thiện bản thân",
        "html": "",
        "comments": "",
        "comments_html": "",
        "weight": 100.0
      },
      {
        "id": 1629,
        "text": "An toàn",
        "html": "",
        "comments": "",
        "comments_html": "",
        "weight": 0.0
      },
      {
        "id": 9923,
        "text": "Được yêu thương",
        "html": "",
        "comments": "",
        "comments_html": "",
        "weight": 0.0
      },
      {
        "id": 6602,
        "text": "Sinh lý",
        "html": "",
        "comments": "",
        "comments_html": "",
        "weight": 0.0
      }
    ],
    "variables": null,
    "formulas": null,
    "answer_tolerance": null,
    "formula_decimal_places": null,
    "matches": null,
    "matching_answer_incorrect_matches": null
  },
  {
    "id": 1126,
    "quiz_id": 122,
    "quiz_group_id": null,
    "assessment_question_id": 1126,
    "position": null,
    "question_name": "Câu hỏi",
    "question_type": "multiple_choice_question",
    "question_text": "<p>Thuyết hai yếu tố Herzberg chia thành:</p>",
    "points_possible": 1.0,
    "correct_comments": "",
    "incorrect_comments": "",
    "neutral_comments": "",
    "correct_comments_html": "",
    "incorrect_comments_html": "",
    "neutral_comments_html": "",
    "answers": [
      {
        "id": 5241,
        "text": "Yếu tố duy trì và yếu tố thúc đẩy",
        "html": "",
        "comments": "",
        "comments_html": "",
        "weight": 100.0
      },
      {
        "id": 5880,
        "text": "Nhu cầu thấp và nhu cầu cao",
        "html": "",
        "comments": "",
        "comments_html": "",
        "weight": 0.0
      },
      {
        "id": 6328,
        "text": "Khen thưởng và kỷ luật",
        "html": "",
        "comments": "",
        "comments_html": "",
        "weight": 0.0
      },
      {
        "id": 6939,
        "text": "Tài chính và phi tài chính",
        "html": "",
        "comments": "",
        "comments_html": "",
        "weight": 0.0
      }
    ],
    "variables": null,
    "formulas": null,
    "answer_tolerance": null,
    "formula_decimal_places": null,
    "matches": null,
    "matching_answer_incorrect_matches": null
  },
  {
    "id": 1127,
    "quiz_id": 122,
    "quiz_group_id": null,
    "assessment_question_id": 1127,
    "position": null,
    "question_name": "Câu hỏi",
    "question_type": "multiple_choice_question",
    "question_text": "<p>Khi nhóm đạt hiệu suất cao và tự vận hành, đó là giai đoạn nào trong Tuckman?</p>",
    "points_possible": 1.0,
    "correct_comments": "",
    "incorrect_comments": "",
    "neutral_comments": "",
    "correct_comments_html": "",
    "incorrect_comments_html": "",
    "neutral_comments_html": "",
    "answers": [
      {
        "id": 8624,
        "text": "Performing",
        "html": "",
        "comments": "",
        "comments_html": "",
        "weight": 100.0
      },
      {
        "id": 2106,
        "text": "Norming",
        "html": "",
        "comments": "",
        "comments_html": "",
        "weight": 0.0
      },
      {
        "id": 6991,
        "text": "Forming",
        "html": "",
        "comments": "",
        "comments_html": "",
        "weight": 0.0
      },
      {
        "id": 4910,
        "text": "Storming",
        "html": "",
        "comments": "",
        "comments_html": "",
        "weight": 0.0
      }
    ],
    "variables": null,
    "formulas": null,
    "answer_tolerance": null,
    "formula_decimal_places": null,
    "matches": null,
    "matching_answer_incorrect_matches": null
  },
  {
    "id": 1128,
    "quiz_id": 122,
    "quiz_group_id": null,
    "assessment_question_id": 1128,
    "position": null,
    "question_name": "Câu hỏi",
    "question_type": "multiple_choice_question",
    "question_text": "<p>Trong cấu trúc tổ chức nào PM có quyền cao nhất?</p>",
    "points_possible": 1.0,
    "correct_comments": "",
    "incorrect_comments": "",
    "neutral_comments": "",
    "correct_comments_html": "",
    "incorrect_comments_html": "",
    "neutral_comments_html": "",
    "answers": [
      {
        "id": 5316,
        "text": "Projectized",
        "html": "",
        "comments": "",
        "comments_html": "",
        "weight": 100.0
      },
      {
        "id": 5674,
        "text": "Matrix",
        "html": "",
        "comments": "",
        "comments_html": "",
        "weight": 0.0
      },
      {
        "id": 1859,
        "text": "Functional",
        "html": "",
        "comments": "",
        "comments_html": "",
        "weight": 0.0
      },
      {
        "id": 3689,
        "text": "Hybrid",
        "html": "",
        "comments": "",
        "comments_html": "",
        "weight": 0.0
      }
    ],
    "variables": null,
    "formulas": null,
    "answer_tolerance": null,
    "formula_decimal_places": null,
    "matches": null,
    "matching_answer_incorrect_matches": null
  },
  {
    "id": 1129,
    "quiz_id": 122,
    "quiz_group_id": null,
    "assessment_question_id": 1129,
    "position": null,
    "question_name": "Câu hỏi",
    "question_type": "multiple_choice_question",
    "question_text": "<p>Phong cách lãnh đạo nào phù hợp với nhóm có kinh nghiệm cao?</p>",
    "points_possible": 1.0,
    "correct_comments": "",
    "incorrect_comments": "",
    "neutral_comments": "",
    "correct_comments_html": "",
    "incorrect_comments_html": "",
    "neutral_comments_html": "",
    "answers": [
      {
        "id": 8402,
        "text": "Ủy quyền (Delegating)",
        "html": "",
        "comments": "",
        "comments_html": "",
        "weight": 100.0
      },
      {
        "id": 2328,
        "text": "Chỉ huy (Directing)",
        "html": "",
        "comments": "",
        "comments_html": "",
        "weight": 0.0
      },
      {
        "id": 9198,
        "text": "Huấn luyện (Coaching)",
        "html": "",
        "comments": "",
        "comments_html": "",
        "weight": 0.0
      },
      {
        "id": 5645,
        "text": "Hỗ trợ (Supporting)",
        "html": "",
        "comments": "",
        "comments_html": "",
        "weight": 0.0
      }
    ],
    "variables": null,
    "formulas": null,
    "answer_tolerance": null,
    "formula_decimal_places": null,
    "matches": null,
    "matching_answer_incorrect_matches": null
  },
  {
    "id": 1130,
    "quiz_id": 122,
    "quiz_group_id": null,
    "assessment_question_id": 1130,
    "position": null,
    "question_name": "Câu hỏi",
    "question_type": "multiple_choice_question",
    "question_text": "<p>PM dành khoảng bao nhiêu phần trăm thời gian cho giao tiếp?</p>",
    "points_possible": 1.0,
    "correct_comments": "",
    "incorrect_comments": "",
    "neutral_comments": "",
    "correct_comments_html": "",
    "incorrect_comments_html": "",
    "neutral_comments_html": "",
    "answers": [
      {
        "id": 7727,
        "text": "80%",
        "html": "",
        "comments": "",
        "comments_html": "",
        "weight": 100.0
      },
      {
        "id": 9623,
        "text": "50%",
        "html": "",
        "comments": "",
        "comments_html": "",
        "weight": 0.0
      },
      {
        "id": 2548,
        "text": "30%",
        "html": "",
        "comments": "",
        "comments_html": "",
        "weight": 0.0
      },
      {
        "id": 9841,
        "text": "90%",
        "html": "",
        "comments": "",
        "comments_html": "",
        "weight": 0.0
      }
    ],
    "variables": null,
    "formulas": null,
    "answer_tolerance": null,
    "formula_decimal_places": null,
    "matches": null,
    "matching_answer_incorrect_matches": null
  },
  {
    "id": 1131,
    "quiz_id": 122,
    "quiz_group_id": null,
    "assessment_question_id": 1131,
    "position": null,
    "question_name": "Câu hỏi",
    "question_type": "multiple_choice_question",
    "question_text": "<p>Trong mô hình Matrix, nhân viên có thể báo cáo cho:</p>",
    "points_possible": 1.0,
    "correct_comments": "",
    "incorrect_comments": "",
    "neutral_comments": "",
    "correct_comments_html": "",
    "incorrect_comments_html": "",
    "neutral_comments_html": "",
    "answers": [
      {
        "id": 3060,
        "text": "Cả PM và Trưởng phòng chức năng",
        "html": "",
        "comments": "",
        "comments_html": "",
        "weight": 100.0
      },
      {
        "id": 4883,
        "text": "Chỉ PM",
        "html": "",
        "comments": "",
        "comments_html": "",
        "weight": 0.0
      },
      {
        "id": 7208,
        "text": "Chỉ CEO",
        "html": "",
        "comments": "",
        "comments_html": "",
        "weight": 0.0
      },
      {
        "id": 2066,
        "text": "Không ai",
        "html": "",
        "comments": "",
        "comments_html": "",
        "weight": 0.0
      }
    ],
    "variables": null,
    "formulas": null,
    "answer_tolerance": null,
    "formula_decimal_places": null,
    "matches": null,
    "matching_answer_incorrect_matches": null
  },
  {
    "id": 1132,
    "quiz_id": 122,
    "quiz_group_id": null,
    "assessment_question_id": 1132,
    "position": null,
    "question_name": "Câu hỏi",
    "question_type": "multiple_choice_question",
    "question_text": "<p>Yếu tố nào KHÔNG thuộc nhóm 'động lực' trong Herzberg?</p>",
    "points_possible": 1.0,
    "correct_comments": "",
    "incorrect_comments": "",
    "neutral_comments": "",
    "correct_comments_html": "",
    "incorrect_comments_html": "",
    "neutral_comments_html": "",
    "answers": [
      {
        "id": 4598,
        "text": "Lương và điều kiện làm việc",
        "html": "",
        "comments": "",
        "comments_html": "",
        "weight": 100.0
      },
      {
        "id": 6764,
        "text": "Ghi nhận thành tích",
        "html": "",
        "comments": "",
        "comments_html": "",
        "weight": 0.0
      },
      {
        "id": 8952,
        "text": "Trách nhiệm",
        "html": "",
        "comments": "",
        "comments_html": "",
        "weight": 0.0
      },
      {
        "id": 3718,
        "text": "Cơ hội phát triển",
        "html": "",
        "comments": "",
        "comments_html": "",
        "weight": 0.0
      }
    ],
    "variables": null,
    "formulas": null,
    "answer_tolerance": null,
    "formula_decimal_places": null,
    "matches": null,
    "matching_answer_incorrect_matches": null
  },
  {
    "id": 1133,
    "quiz_id": 122,
    "quiz_group_id": null,
    "assessment_question_id": 1133,
    "position": null,
    "question_name": "Câu hỏi",
    "question_type": "multiple_choice_question",
    "question_text": "<p>Cách xử lý xung đột 'Compromising' có nghĩa là:</p>",
    "points_possible": 1.0,
    "correct_comments": "",
    "incorrect_comments": "",
    "neutral_comments": "",
    "correct_comments_html": "",
    "incorrect_comments_html": "",
    "neutral_comments_html": "",
    "answers": [
      {
        "id": 839,
        "text": "Hai bên cùng nhượng bộ một phần",
        "html": "",
        "comments": "",
        "comments_html": "",
        "weight": 100.0
      },
      {
        "id": 1297,
        "text": "Tránh né hoàn toàn",
        "html": "",
        "comments": "",
        "comments_html": "",
        "weight": 0.0
      },
      {
        "id": 5754,
        "text": "Một bên thắng, một bên thua",
        "html": "",
        "comments": "",
        "comments_html": "",
        "weight": 0.0
      },
      {
        "id": 6986,
        "text": "Không đưa ra quyết định",
        "html": "",
        "comments": "",
        "comments_html": "",
        "weight": 0.0
      }
    ],
    "variables": null,
    "formulas": null,
    "answer_tolerance": null,
    "formula_decimal_places": null,
    "matches": null,
    "matching_answer_incorrect_matches": null
  },
  {
    "id": 1134,
    "quiz_id": 122,
    "quiz_group_id": null,
    "assessment_question_id": 1134,
    "position": null,
    "question_name": "Câu hỏi",
    "question_type": "multiple_choice_question",
    "question_text": "<p>Trong lý thuyết McGregor, thuyết Y nhấn mạnh điều gì?</p>",
    "points_possible": 1.0,
    "correct_comments": "",
    "incorrect_comments": "",
    "neutral_comments": "",
    "correct_comments_html": "",
    "incorrect_comments_html": "",
    "neutral_comments_html": "",
    "answers": [
      {
        "id": 9530,
        "text": "Con người tự giác, có trách nhiệm",
        "html": "",
        "comments": "",
        "comments_html": "",
        "weight": 100.0
      },
      {
        "id": 5751,
        "text": "Con người cần giám sát liên tục",
        "html": "",
        "comments": "",
        "comments_html": "",
        "weight": 0.0
      },
      {
        "id": 6550,
        "text": "Con người lười biếng",
        "html": "",
        "comments": "",
        "comments_html": "",
        "weight": 0.0
      },
      {
        "id": 7437,
        "text": "Con người chỉ làm vì tiền",
        "html": "",
        "comments": "",
        "comments_html": "",
        "weight": 0.0
      }
    ],
    "variables": null,
    "formulas": null,
    "answer_tolerance": null,
    "formula_decimal_places": null,
    "matches": null,
    "matching_answer_incorrect_matches": null
  },
  {
    "id": 1135,
    "quiz_id": 122,
    "quiz_group_id": null,
    "assessment_question_id": 1135,
    "position": null,
    "question_name": "Câu hỏi",
    "question_type": "multiple_choice_question",
    "question_text": "<p>Khi nhóm mới được hình thành, phong cách lãnh đạo nên là:</p>",
    "points_possible": 1.0,
    "correct_comments": "",
    "incorrect_comments": "",
    "neutral_comments": "",
    "correct_comments_html": "",
    "incorrect_comments_html": "",
    "neutral_comments_html": "",
    "answers": [
      {
        "id": 9157,
        "text": "Chỉ huy (Directing)",
        "html": "",
        "comments": "",
        "comments_html": "",
        "weight": 100.0
      },
      {
        "id": 6721,
        "text": "Ủy quyền (Delegating)",
        "html": "",
        "comments": "",
        "comments_html": "",
        "weight": 0.0
      },
      {
        "id": 620,
        "text": "Hợp tác",
        "html": "",
        "comments": "",
        "comments_html": "",
        "weight": 0.0
      },
      {
        "id": 53,
        "text": "Thỏa hiệp",
        "html": "",
        "comments": "",
        "comments_html": "",
        "weight": 0.0
      }
    ],
    "variables": null,
    "formulas": null,
    "answer_tolerance": null,
    "formula_decimal_places": null,
    "matches": null,
    "matching_answer_incorrect_matches": null
  },
  {
    "id": 1136,
    "quiz_id": 122,
    "quiz_group_id": null,
    "assessment_question_id": 1136,
    "position": null,
    "question_name": "Câu hỏi",
    "question_type": "multiple_choice_question",
    "question_text": "<p>Biện pháp hiệu quả nhất khi nhóm có xung đột lợi ích?</p>",
    "points_possible": 1.0,
    "correct_comments": "",
    "incorrect_comments": "",
    "neutral_comments": "",
    "correct_comments_html": "",
    "incorrect_comments_html": "",
    "neutral_comments_html": "",
    "answers": [
      {
        "id": 3982,
        "text": "Hợp tác (Collaborating)",
        "html": "",
        "comments": "",
        "comments_html": "",
        "weight": 100.0
      },
      {
        "id": 8842,
        "text": "Tránh né",
        "html": "",
        "comments": "",
        "comments_html": "",
        "weight": 0.0
      },
      {
        "id": 8796,
        "text": "Thỏa hiệp",
        "html": "",
        "comments": "",
        "comments_html": "",
        "weight": 0.0
      },
      {
        "id": 3432,
        "text": "Áp đặt",
        "html": "",
        "comments": "",
        "comments_html": "",
        "weight": 0.0
      }
    ],
    "variables": null,
    "formulas": null,
    "answer_tolerance": null,
    "formula_decimal_places": null,
    "matches": null,
    "matching_answer_incorrect_matches": null
  },
  {
    "id": 1137,
    "quiz_id": 122,
    "quiz_group_id": null,
    "assessment_question_id": 1137,
    "position": null,
    "question_name": "Câu hỏi",
    "question_type": "multiple_choice_question",
    "question_text": "<p>Theo Herzberg, yếu tố nào giúp duy trì sự hài lòng nhưng không tạo động lực?</p>",
    "points_possible": 1.0,
    "correct_comments": "",
    "incorrect_comments": "",
    "neutral_comments": "",
    "correct_comments_html": "",
    "incorrect_comments_html": "",
    "neutral_comments_html": "",
    "answers": [
      {
        "id": 2998,
        "text": "Lương",
        "html": "",
        "comments": "",
        "comments_html": "",
        "weight": 100.0
      },
      {
        "id": 8820,
        "text": "Thành tích",
        "html": "",
        "comments": "",
        "comments_html": "",
        "weight": 0.0
      },
      {
        "id": 8088,
        "text": "Thách thức",
        "html": "",
        "comments": "",
        "comments_html": "",
        "weight": 0.0
      },
      {
        "id": 9857,
        "text": "Trách nhiệm",
        "html": "",
        "comments": "",
        "comments_html": "",
        "weight": 0.0
      }
    ],
    "variables": null,
    "formulas": null,
    "answer_tolerance": null,
    "formula_decimal_places": null,
    "matches": null,
    "matching_answer_incorrect_matches": null
  },
  {
    "id": 1138,
    "quiz_id": 122,
    "quiz_group_id": null,
    "assessment_question_id": 1138,
    "position": null,
    "question_name": "Câu hỏi",
    "question_type": "multiple_choice_question",
    "question_text": "<p>Giai đoạn 'Norming' trong Tuckman biểu thị:</p>",
    "points_possible": 1.0,
    "correct_comments": "",
    "incorrect_comments": "",
    "neutral_comments": "",
    "correct_comments_html": "",
    "incorrect_comments_html": "",
    "neutral_comments_html": "",
    "answers": [
      {
        "id": 3838,
        "text": "Nhóm bắt đầu hợp tác ổn định",
        "html": "",
        "comments": "",
        "comments_html": "",
        "weight": 100.0
      },
      {
        "id": 1882,
        "text": "Nhóm tan rã",
        "html": "",
        "comments": "",
        "comments_html": "",
        "weight": 0.0
      },
      {
        "id": 2523,
        "text": "Nhóm xung đột mạnh",
        "html": "",
        "comments": "",
        "comments_html": "",
        "weight": 0.0
      },
      {
        "id": 1662,
        "text": "Nhóm đạt hiệu suất tối đa",
        "html": "",
        "comments": "",
        "comments_html": "",
        "weight": 0.0
      }
    ],
    "variables": null,
    "formulas": null,
    "answer_tolerance": null,
    "formula_decimal_places": null,
    "matches": null,
    "matching_answer_incorrect_matches": null
  },
  {
    "id": 1139,
    "quiz_id": 122,
    "quiz_group_id": null,
    "assessment_question_id": 1139,
    "position": null,
    "question_name": "Câu hỏi",
    "question_type": "multiple_choice_question",
    "question_text": "<p>Nếu PM quá chú trọng kỹ thuật mà bỏ qua giao tiếp nhóm, điều gì có thể xảy ra?</p>",
    "points_possible": 1.0,
    "correct_comments": "",
    "incorrect_comments": "",
    "neutral_comments": "",
    "correct_comments_html": "",
    "incorrect_comments_html": "",
    "neutral_comments_html": "",
    "answers": [
      {
        "id": 4391,
        "text": "Giảm tinh thần nhóm và hiệu suất",
        "html": "",
        "comments": "",
        "comments_html": "",
        "weight": 100.0
      },
      {
        "id": 3212,
        "text": "Tăng năng suất",
        "html": "",
        "comments": "",
        "comments_html": "",
        "weight": 0.0
      },
      {
        "id": 7790,
        "text": "Giảm chi phí",
        "html": "",
        "comments": "",
        "comments_html": "",
        "weight": 0.0
      },
      {
        "id": 4434,
        "text": "Rút ngắn tiến độ",
        "html": "",
        "comments": "",
        "comments_html": "",
        "weight": 0.0
      }
    ],
    "variables": null,
    "formulas": null,
    "answer_tolerance": null,
    "formula_decimal_places": null,
    "matches": null,
    "matching_answer_incorrect_matches": null
  },
  {
    "id": 1140,
    "quiz_id": 122,
    "quiz_group_id": null,
    "assessment_question_id": 1140,
    "position": null,
    "question_name": "Câu hỏi",
    "question_type": "multiple_choice_question",
    "question_text": "<p>Yếu tố nào quyết định sự thành công trong phát triển nhóm?</p>",
    "points_possible": 1.0,
    "correct_comments": "",
    "incorrect_comments": "",
    "neutral_comments": "",
    "correct_comments_html": "",
    "incorrect_comments_html": "",
    "neutral_comments_html": "",
    "answers": [
      {
        "id": 588,
        "text": "Lãnh đạo và giao tiếp hiệu quả",
        "html": "",
        "comments": "",
        "comments_html": "",
        "weight": 100.0
      },
      {
        "id": 9273,
        "text": "Tài chính mạnh",
        "html": "",
        "comments": "",
        "comments_html": "",
        "weight": 0.0
      },
      {
        "id": 6289,
        "text": "Phần mềm hỗ trợ",
        "html": "",
        "comments": "",
        "comments_html": "",
        "weight": 0.0
      },
      {
        "id": 5327,
        "text": "Hệ thống KPI",
        "html": "",
        "comments": "",
        "comments_html": "",
        "weight": 0.0
      }
    ],
    "variables": null,
    "formulas": null,
    "answer_tolerance": null,
    "formula_decimal_places": null,
    "matches": null,
    "matching_answer_incorrect_matches": null
  },
  {
    "id": 1141,
    "quiz_id": 122,
    "quiz_group_id": null,
    "assessment_question_id": 1141,
    "position": null,
    "question_name": "Câu hỏi",
    "question_type": "multiple_choice_question",
    "question_text": "<p>Khi nhóm đạt giai đoạn Performing, vai trò của PM là:</p>",
    "points_possible": 1.0,
    "correct_comments": "",
    "incorrect_comments": "",
    "neutral_comments": "",
    "correct_comments_html": "",
    "incorrect_comments_html": "",
    "neutral_comments_html": "",
    "answers": [
      {
        "id": 3474,
        "text": "Giám sát nhẹ, tập trung điều phối và hỗ trợ",
        "html": "",
        "comments": "",
        "comments_html": "",
        "weight": 100.0
      },
      {
        "id": 9768,
        "text": "Kiểm soát chặt chẽ từng người",
        "html": "",
        "comments": "",
        "comments_html": "",
        "weight": 0.0
      },
      {
        "id": 5134,
        "text": "Tăng áp lực",
        "html": "",
        "comments": "",
        "comments_html": "",
        "weight": 0.0
      },
      {
        "id": 7222,
        "text": "Tách nhóm",
        "html": "",
        "comments": "",
        "comments_html": "",
        "weight": 0.0
      }
    ],
    "variables": null,
    "formulas": null,
    "answer_tolerance": null,
    "formula_decimal_places": null,
    "matches": null,
    "matching_answer_incorrect_matches": null
  }
]